pxng/__init__.py
pxng/_utils.py
pxng/animated_sprite.py
pxng/buffer_object.py
pxng/colors.py
pxng/display_list.py
pxng/font.py
pxng/grid.py
pxng/keys.py
pxng/mouse.py
pxng/opengl.py
pxng/quad.py
pxng/shader.py
pxng/spaces.py
pxng/sprite.py
pxng/text_renderer.py
pxng/vertex_array_object.py
pxng/window.py
pxng/resources/fonts/C64_Pro_Mono-STYLE.ttf
pxng/resources/shaders/font.frag
pxng/resources/shaders/font.geom
pxng/resources/shaders/font.vert
pxng/resources/shaders/line.frag
pxng/resources/shaders/line.vert
pxng/resources/shaders/quad.frag
pxng/resources/shaders/quad.vert
pxng/resources/shaders/sprite.frag
pxng/resources/shaders/sprite.vert
pxng-0.0.13.dist-info/LICENSE.md
pxng-0.0.13.dist-info/METADATA
pxng-0.0.13.dist-info/WHEEL
pxng-0.0.13.dist-info/top_level.txt
pxng-0.0.13.dist-info/RECORD
