Metadata-Version: 2.1
Name: pxng
Version: 0.0.13
Summary: A library for fiddling with pixels
Home-page: https://github.com/jepebe/pixelengine
Author: Jean-Paul Balabanian
Author-email: jepebe@prador.net
License: BSD
Platform: UNKNOWN
Classifier: Programming Language :: Python :: 3
Classifier: License :: OSI Approved :: BSD License
Classifier: Operating System :: OS Independent
Requires-Python: >=3.6
Requires-Dist: glfw (>=2.0.0)
Requires-Dist: pyopengl (>=3.1.0)
Requires-Dist: freetype-py (>=2.2.0)
Requires-Dist: numpy (>=1.19.0)
Requires-Dist: imageio (>=2.9.0)
Requires-Dist: pyglm (>=1.99.0)
Requires-Dist: dataclasses ; python_version < "3.7"
